Metadata-Version: 1.0
Name: bishajit-distributions
Version: 0.2
Summary: Gaussian and binomial distributions
Home-page: UNKNOWN
Author: Bishajit Lodh
Author-email: Bishajitklodh@gmail.com
License: UNKNOWN
Platform: UNKNOWN
